pypgoutput/__init__.py
pypgoutput/decoders.py
pypgoutput/reader.py
pypgoutput/utils.py
pypgoutput-0.0.3.dist-info/LICENSE
pypgoutput-0.0.3.dist-info/METADATA
pypgoutput-0.0.3.dist-info/WHEEL
pypgoutput-0.0.3.dist-info/top_level.txt
pypgoutput-0.0.3.dist-info/RECORD
