Metadata-Version: 2.1
Name: pypgoutput
Version: 0.0.3
Summary: PostgreSQL CDC library using pgoutput and python
Home-page: https://github.com/dgea005/pypgoutput
Author: Daniel Geals
Author-email: danielgeals@gmail.com
License: UNKNOWN
Platform: UNKNOWN
Classifier: Programming Language :: Python :: 3
Classifier: Programming Language :: Python :: 3.8
Classifier: Programming Language :: Python :: 3.9
Classifier: Programming Language :: Python :: 3.10
Classifier: License :: OSI Approved :: MIT License
Classifier: Operating System :: OS Independent
Requires-Python: >=3.8
License-File: LICENSE
Requires-Dist: psycopg2
Requires-Dist: pydantic
